metricx/__init__.py
metricx/grid.py
metricx/metric.py
metricx/selector.py
metricx/task.py
metricx-0.0.2.dist-info/LICENSE
metricx-0.0.2.dist-info/METADATA
metricx-0.0.2.dist-info/WHEEL
metricx-0.0.2.dist-info/top_level.txt
metricx-0.0.2.dist-info/RECORD
